setup.py
cloudmesh_timestring.egg-info/PKG-INFO
cloudmesh_timestring.egg-info/SOURCES.txt
cloudmesh_timestring.egg-info/dependency_links.txt
cloudmesh_timestring.egg-info/entry_points.txt
cloudmesh_timestring.egg-info/requires.txt
cloudmesh_timestring.egg-info/top_level.txt
cloudmesh_timestring.egg-info/zip-safe
timestring/Date.py
timestring/Range.py
timestring/__init__.py
timestring/text2num.py
timestring/timestring_re.py